vvgen_generatepass/__init__.py
vvgen_generatepass/core.py
vvgen_generatepass-0.0.3.dist-info/METADATA
vvgen_generatepass-0.0.3.dist-info/WHEEL
vvgen_generatepass-0.0.3.dist-info/top_level.txt
vvgen_generatepass-0.0.3.dist-info/RECORD
