Metadata-Version: 2.1
Name: vvgen_generatepass
Version: 0.0.3
Summary: A secure password generator
Author: Nikita
Author-email: firi8228@gmail.com
Classifier: Programming Language :: Python :: 3
Classifier: License :: OSI Approved :: MIT License
Classifier: Operating System :: OS Independent
Requires-Dist: cryptography
